ionized/__init__.py
ionized/ionized.py
ionized-1.1.0.dist-info/AUTHORS.rst
ionized-1.1.0.dist-info/LICENSE
ionized-1.1.0.dist-info/METADATA
ionized-1.1.0.dist-info/WHEEL
ionized-1.1.0.dist-info/top_level.txt
ionized-1.1.0.dist-info/RECORD
