Metadata-Version: 2.1
Name: ionized
Version: 1.1.0
Summary: Bootstrap Amazon Ion into existing projects
Home-page: https://github.com/tbobm/ionized
Author: Theo "Bob" Massard
Author-email: tbobm@protonmail.com
License: Apache Software License 2.0
Keywords: ionized
Platform: UNKNOWN
Classifier: Development Status :: 2 - Pre-Alpha
Classifier: Intended Audience :: Developers
Classifier: License :: OSI Approved :: Apache Software License
Classifier: Natural Language :: English
Classifier: Programming Language :: Python :: 3
Classifier: Programming Language :: Python :: 3.6
Classifier: Programming Language :: Python :: 3.7
Classifier: Programming Language :: Python :: 3.8
Requires-Python: >=3.6
License-File: LICENSE
License-File: AUTHORS.rst
Requires-Dist: amazon.ion
